{
  "name": "Lion's Liquor",
  "source": "TftJC",
  "type": "FD",
  "rarity": "uncommon",
  "value": 3000,
  "weight": 0,
  "entries": [
    "<b>Preparation:</b> Requires Brewer's Tools to prepare.",
    "<b>Ingredients:</b> x1 Red Winter Berry, x1 Devils Cactus",
    "<b>Effect:</b> You have advantage on any saving throws made to resist fear not caused by spells."
  ],
  "foundryType": "consumable",
  "foundrySystem": {
    "consumableType": "food",
    "uses": {
      "max": 1,
      "per": null,
      "autoDestroy": true,
      "value": 1
    }
  },
  "foundryActivities": [
    {
      "foundryId": "consumelionsliquor",
      "type": "utility",
      "name": "Consume Lion's Liquor",
      "description": { "chatFlavor": "Advantage on saves vs non-spell fear." },
      "consumption": { "targets": [{ "target": "uses", "value": "1" }] }
    }
  ]
}
